{
  "name_of_RSA": "state-only_excluding_rewA",
  "regression_version": "03-4",
  "EV_condition_selection": {
    "parts": {
      "task":      { "include": [],          "exclude": ["B*", "D*"]},
      "direction": { "include": [],          "exclude": [] },
      "state":     { "include": [], "exclude": ["A"] },
      "phase":     { "include": [],   "exclude": [] }
    },
  },
  "models": ["state"],
  "smoothing": true,
  "fwhm": 5,
  "load_searchlights": true,
  "visualise_RDMs": false,
  "run_combo_models": false,
}


